noaaco2.py
noaaco2-0.0.4.dist-info/METADATA
noaaco2-0.0.4.dist-info/WHEEL
noaaco2-0.0.4.dist-info/entry_points.txt
noaaco2-0.0.4.dist-info/top_level.txt
noaaco2-0.0.4.dist-info/RECORD
