Metadata-Version: 2.1
Name: noaaco2
Version: 0.0.4
Summary: A package for displaying co2 graph based on NOAA
Home-page: https://github.com/y-takefuji/noaaco2
Author: yoshiyasu takefuji
Author-email: takefuji@keio.jp
License: UNKNOWN
Project-URL: Bug Tracker, https://github.com/y-takefuji/noaaco2
Platform: UNKNOWN
Classifier: Programming Language :: Python :: 3
Classifier: License :: OSI Approved :: MIT License
Classifier: Operating System :: OS Independent
Requires-Python: >=3.8
